cookiecutter.json
filters.py
hooks/post_gen_project.py
hooks/pre_gen_project.py
package_helper_3/__init__.py
package_helper_3/cli.py
package_helper_3/foo.py
{{cookiecutter.project_slug}}/.coveragerc
{{cookiecutter.project_slug}}/.editorconfig
{{cookiecutter.project_slug}}/.gitignore
{{cookiecutter.project_slug}}/AUTHORS.md
{{cookiecutter.project_slug}}/CONTRIBUTING.md
{{cookiecutter.project_slug}}/Dockerfile
{{cookiecutter.project_slug}}/HISTORY.md
{{cookiecutter.project_slug}}/README.md
{{cookiecutter.project_slug}}/citation.cff
{{cookiecutter.project_slug}}/pyproject.toml
{{cookiecutter.project_slug}}/.github/ISSUE_TEMPLATE.md
{{cookiecutter.project_slug}}/.github/workflows/build.yml
{{cookiecutter.project_slug}}/.github/workflows/docs.yml
{{cookiecutter.project_slug}}/.github/workflows/release.yml
{{cookiecutter.project_slug}}/.run/All tests.run.xml
{{cookiecutter.project_slug}}/.run/Generate docs.run.xml
{{cookiecutter.project_slug}}/docs/conf.py
{{cookiecutter.project_slug}}/docs/index.md
{{cookiecutter.project_slug}}/docs/presentation/authors.md
{{cookiecutter.project_slug}}/docs/presentation/contributing.md
{{cookiecutter.project_slug}}/docs/presentation/history.md
{{cookiecutter.project_slug}}/docs/presentation/index.md
{{cookiecutter.project_slug}}/docs/presentation/installation.md
{{cookiecutter.project_slug}}/docs/presentation/readme.md
{{cookiecutter.project_slug}}/docs/reference/index.md
{{cookiecutter.project_slug}}/docs/reference/my_class_1.md
{{cookiecutter.project_slug}}/docs/reference/my_class_2.md
{{cookiecutter.project_slug}}/docs/reference/my_class_3.md
{{cookiecutter.project_slug}}/docs/tutorials/answer.ipynb
{{cookiecutter.project_slug}}/docs/tutorials/index.md
{{cookiecutter.project_slug}}/docs/tutorials/tutorial.ipynb
{{cookiecutter.project_slug}}/tests/__init__.py
{{cookiecutter.project_slug}}/tests/test_{{cookiecutter.project_slug}}.py
{{cookiecutter.project_slug}}/{{cookiecutter.package_name}}/__init__.py
package_helper_3-0.4.5.dist-info/METADATA
package_helper_3-0.4.5.dist-info/WHEEL
package_helper_3-0.4.5.dist-info/entry_points.txt
package_helper_3-0.4.5.dist-info/licenses/AUTHORS.md
package_helper_3-0.4.5.dist-info/RECORD
