Metadata-Version: 2.4
Name: package-helper-3
Version: 0.4.5
Summary: Package Helper 3 helps to create, develop, and maintain a Python package with UV.
Project-URL: repository, https://github.com/balouf/package-helper-3
Project-URL: documentation, https://balouf.github.io/package-helper-3/
Author-email: Fabien Mathieu <fabien.mathieu@normalesup.org>
Maintainer-email: Fabien Mathieu <fabien.mathieu@normalesup.org>
License-Expression: MIT
License-File: AUTHORS.md
Requires-Python: >=3.10
Requires-Dist: click>=8.1.8
Requires-Dist: cookiecutter>=2.6.0
